kubeconf/__init__.py
kubeconf/kubeconf.py
kubeconf-0.0.5.dist-info/LICENSE
kubeconf-0.0.5.dist-info/METADATA
kubeconf-0.0.5.dist-info/WHEEL
kubeconf-0.0.5.dist-info/top_level.txt
kubeconf-0.0.5.dist-info/RECORD
