Metadata-Version: 2.1
Name: kubeconf
Version: 0.0.5
Summary: Lightweight Python module for creating, manipulating, and editing kubeconfig files
Home-page: https://github.com/Zsailer/kubeconf
Author: Zach Sailer
Author-email: zachsailer@gmail.com
License: MIT
Platform: UNKNOWN
Classifier: License :: OSI Approved :: MIT License
Classifier: Programming Language :: Python
Classifier: Programming Language :: Python :: 3
Classifier: Programming Language :: Python :: 3.6
Classifier: Programming Language :: Python :: Implementation :: CPython
Classifier: Programming Language :: Python :: Implementation :: PyPy
